desktop_notifier/__init__.py
desktop_notifier/common.py
desktop_notifier/main.py
desktop_notifier/py.typed
desktop_notifier/sync.py
desktop_notifier/backends/__init__.py
desktop_notifier/backends/base.py
desktop_notifier/backends/dbus.py
desktop_notifier/backends/dummy.py
desktop_notifier/backends/macos.py
desktop_notifier/backends/macos_support.py
desktop_notifier/backends/winrt.py
desktop_notifier/resources/__init__.py
desktop_notifier/resources/python.png
desktop_notifier-6.1.1.dist-info/licenses/LICENSE
desktop_notifier-6.1.1.dist-info/METADATA
desktop_notifier-6.1.1.dist-info/WHEEL
desktop_notifier-6.1.1.dist-info/top_level.txt
desktop_notifier-6.1.1.dist-info/RECORD
