Metadata-Version: 2.4
Name: desktop-notifier
Version: 6.1.1
Summary: Python library for cross-platform desktop notifications
Author-email: Sam Schott <sam.schott@outlook.com>
License-Expression: MIT
Project-URL: Homepage, https://github.com/samschott/desktop-notifier
Keywords: desktop-notifier,notifications,Notification Center,push notifications,Toast notifications
Classifier: Development Status :: 5 - Production/Stable
Classifier: Intended Audience :: Developers
Classifier: Natural Language :: English
Classifier: Operating System :: MacOS :: MacOS X
Classifier: Operating System :: Microsoft :: Windows
Classifier: Operating System :: OS Independent
Classifier: Programming Language :: Python :: 3
Classifier: Programming Language :: Python :: 3.9
Classifier: Programming Language :: Python :: 3.10
Classifier: Programming Language :: Python :: 3.11
Classifier: Programming Language :: Python :: 3.12
Classifier: Programming Language :: Python :: 3.13
Classifier: Programming Language :: Python :: 3 :: Only
Classifier: Topic :: Communications
Classifier: Topic :: Desktop Environment
Classifier: Topic :: Desktop Environment :: Gnome
Classifier: Topic :: Desktop Environment :: K Desktop Environment (KDE)
Classifier: Topic :: Software Development :: Libraries :: Python Modules
Requires-Python: >=3.9
License-File: LICENSE
Requires-Dist: bidict
Requires-Dist: packaging
Requires-Dist: typing-extensions
Requires-Dist: dbus-fast; sys_platform == "linux"
Requires-Dist: rubicon-objc>=0.5; sys_platform == "darwin"
Requires-Dist: winrt-runtime>=3.1; sys_platform == "win32"
Requires-Dist: winrt-windows.applicationmodel.core>=3.1; sys_platform == "win32"
Requires-Dist: winrt-windows.data.xml.dom>=3.1; sys_platform == "win32"
Requires-Dist: winrt-windows.foundation>=3.1; sys_platform == "win32"
Requires-Dist: winrt-windows.foundation.collections>=3.1; sys_platform == "win32"
Requires-Dist: winrt-windows.ui.notifications>=3.1; sys_platform == "win32"
Provides-Extra: dev
Requires-Dist: black; extra == "dev"
Requires-Dist: bump2version; extra == "dev"
Requires-Dist: flake8; extra == "dev"
Requires-Dist: flake8-pyproject; extra == "dev"
Requires-Dist: isort; extra == "dev"
Requires-Dist: mypy; extra == "dev"
Requires-Dist: pytest; extra == "dev"
Requires-Dist: pytest-asyncio; extra == "dev"
Requires-Dist: pytest-cov; extra == "dev"
Provides-Extra: docs
Requires-Dist: furo==2024.8.6; extra == "docs"
Requires-Dist: sphinx==8.1.3; extra == "docs"
Requires-Dist: sphinx-autoapi==3.6.0; extra == "docs"
Requires-Dist: sphinx-mdinclude==0.6.2; extra == "docs"
Dynamic: license-file
